{
  "project_info": {
    "project_number": "949303853336",
    "project_id": "chatup-d9d43",
    "storage_bucket": "chatup-d9d43.appspot.com"
  },
  "client": [
    {
      "client_info": {
        "mobilesdk_app_id": "1:949303853336:android:aa84b03ad11b10d109de6d",
        "android_client_info": {
          "package_name": "com.example.chatup"
        }
      },
      "oauth_client": [
        {
          "client_id": "949303853336-2cc6v2puq7gi1770a1o6lehi9c902pdh.apps.googleusercontent.com",
          "client_type": 3
        }
      ],
      "api_key": [
        {
          "current_key": "AIzaSyDFP3IzFZL6zxQHCteYADun5I2BS1npLio"
        }
      ],
      "services": {
        "appinvite_service": {
          "other_platform_oauth_client": [
            {
              "client_id": "949303853336-2cc6v2puq7gi1770a1o6lehi9c902pdh.apps.googleusercontent.com",
              "client_type": 3
            },
            {
              "client_id": "949303853336-genh1on5tlnn2bs756crensr0270jero.apps.googleusercontent.com",
              "client_type": 2,
              "ios_info": {
                "bundle_id": "com.example.instagramCloneFlutter"
              }
            }
          ]
        }
      }
    }
  ],
  "configuration_version": "1"
}